<XML_DIZ_INFO>
  <MASTER_PAD_VERSION_INFO>
    <MASTER_PAD_VERSION>4.0</MASTER_PAD_VERSION>
    <MASTER_PAD_EDITOR>AppVisor 1.0.43</MASTER_PAD_EDITOR>
    <MASTER_PAD_EDITOR_URL>http://publisher.appvisor.com</MASTER_PAD_EDITOR_URL>
    <MASTER_PAD_INFO>Portable Application Description, or PAD(TM) 2004 Association of Software Professionals (ASP)http://www.asp-shareware.org/pad is a data set standard and specification that is commercialsoftware publishers to disseminate certified information about their software application. The PAD format is copyright of the ASP and cannot be used without the formal licensing and permission of both the Association of Software Professionals and its agent AppVisor.com.</MASTER_PAD_INFO>
    <CERTIFIED>No</CERTIFIED>
    <CERTIFICATE_ID></CERTIFICATE_ID>
    <CERTIFICATE_LICENSE></CERTIFICATE_LICENSE>
  </MASTER_PAD_VERSION_INFO>
  <RoboSoft>
    <Company_UIN>CMP-9A00A9C3A35D</Company_UIN>
    <Product_UIN>APP-AA0011FEB35D</Product_UIN>
    <Publish_on_CD>N</Publish_on_CD>
    <NewsFeed_Search_String></NewsFeed_Search_String>
    <Search_String>Subtitle Speech Synchronizer</Search_String>
    <Press_Release_Search_String></Press_Release_Search_String>
    <Backlink></Backlink>
    <Comments_For_Reviewer></Comments_For_Reviewer>
    <Search_String_Unique>Subtitle Speech Synchronizer</Search_String_Unique>
    <Search_Engine_Search_String></Search_Engine_Search_String>
    <Web_Directories_Search_String></Web_Directories_Search_String>
    <Company_Description></Company_Description>
  </RoboSoft>
  <Company_Info>
    <PublisherID>pid-8a00d30a935d</PublisherID>
    <BrandID>bid-9a00a9c3a35d</BrandID>
    <Company_Name>sc0ty</Company_Name>
    <Country>Poland</Country>
    <State_Province>Wielkopolskie</State_Province>
    <City_Town>Poznan</City_Town>
    <Zip_Postal_Code>61-545</Zip_Postal_Code>
    <Address_1>Poznan</Address_1>
    <Address_2></Address_2>
    <Company_WebSite_URL>http://sc0ty.pl</Company_WebSite_URL>
    <Contact_Info>
      <Contact_First_Name>Michal</Contact_First_Name>
      <Contact_Last_Name>Szymaniak</Contact_Last_Name>
      <Contact_Email>sc0typl+subsync@gmail.com</Contact_Email>
      <Author_First_Name>Michal</Author_First_Name>
      <Author_Last_Name>Szymaniak</Author_Last_Name>
      <Author_Email>sc0typl+subsync@gmail.com</Author_Email>
      <Contact_Phone></Contact_Phone>
    </Contact_Info>
    <Support_Info>
      <Sales_Email>sc0typl+subsync@gmail.com</Sales_Email>
      <Support_Email>sc0typl+subsync@gmail.com</Support_Email>
      <General_Email>sc0typl+subsync@gmail.com</General_Email>
      <Sales_Phone></Sales_Phone>
      <Support_Phone></Support_Phone>
      <General_Phone></General_Phone>
      <Fax_Phone></Fax_Phone>
    </Support_Info>
    <GooglePlusPage></GooglePlusPage>
    <LinkedinPage></LinkedinPage>
    <TwitterCompanyPage></TwitterCompanyPage>
    <FacebookCompanyPage></FacebookCompanyPage>
  </Company_Info>
  <Program_Info>
    <AppID>app-aa0011feb35d</AppID>
    <Program_Name>Subtitle Speech Synchronizer</Program_Name>
    <Program_Version>0.5.0</Program_Version>
    <Program_Release_Month>11</Program_Release_Month>
    <Program_Release_Day>06</Program_Release_Day>
    <Program_Release_Year>2018</Program_Release_Year>
    <Program_Cost_Dollars>0</Program_Cost_Dollars>
    <Program_Type>Freeware</Program_Type>
    <Program_Category_Class>Audio &amp; Multimedia::Video Tools</Program_Category_Class>
    <Program_Specific_Category></Program_Specific_Category>
    <Program_Categories>Multimedia and Design :: Utilities,Multimedia and Design :: Miscellaneous,Utilities :: Synchronization,Utilities :: Miscellaneous,MP3 &amp; Audio :: Speech Utilities</Program_Categories>
    <Program_Release_Status>New Release</Program_Release_Status>
    <Program_Install_Support>Install and Uninstall</Program_Install_Support>
    <Program_Target_Platform>Windows</Program_Target_Platform>
    <Program_OS_Support>Win2000,WinXP,Win7 x32,Win7 x64,Windows 8,Windows 10,WinServer,WinOther,Windows2000,Windows2003,Windows Server 2000,Windows Server 2003,Windows Server 2008,Windows Server 2008r2,Windows Server 2012,Windows Tablet PC Edition 2005,Windows Media Center Edition 2005,WinVista,Windows Vista Starter,Windows Vista Home Basic,Windows Vista Home Premium,Windows Vista Business,Windows Vista Enterprise,Windows Vista Ultimate,WinVista x64,Windows Vista Home Basic x64,Windows Vista Home Premium x64,Windows Vista Business x64,Windows Vista Enterprise x64,Windows Vista Ultimate x64</Program_OS_Support>
    <Program_Language>English,Polish</Program_Language>
    <Program_Change_Info>- added Polish translation
- bugfixes and optimization</Program_Change_Info>
    <Program_System_Requirements>Windows 10</Program_System_Requirements>
    <Limitations>unlimited</Limitations>
    <Awards></Awards>
    <File_Info>
      <File_Size_Bytes>68370432</File_Size_Bytes>
      <File_Size_K>66768</File_Size_K>
      <File_Size_MB>65.20</File_Size_MB>
    </File_Info>
    <Expire_Info>
      <Has_Expire_Info>N</Has_Expire_Info>
      <Expire_Count></Expire_Count>
      <Expire_Based_On></Expire_Based_On>
      <Expire_Year></Expire_Year>
      <Expire_Other_Info></Expire_Other_Info>
      <Expire_Month></Expire_Month>
      <Expire_Day></Expire_Day>
    </Expire_Info>
    <Includes_JAVA_VM></Includes_JAVA_VM>
    <Includes_DirectX></Includes_DirectX>
    <Includes_VB_Runtime></Includes_VB_Runtime>
  </Program_Info>
  <Web_Info>
    <Application_URLs>
      <Application_Info_URL>https://sc0ty.github.io/subsync</Application_Info_URL>
      <Application_Order_URL></Application_Order_URL>
      <Application_Screenshot_URL>https://sc0ty.github.io/subsync/img/screen2.png</Application_Screenshot_URL>
      <Application_Icon_URL>http://sc0ty.pl/files/subsync.png</Application_Icon_URL>
      <Application_XML_File_URL>http://repository.appvisor.com/app-aa0011feb35d/site-01/Subtitle_Speech_Synchronizer_pad.xml</Application_XML_File_URL>
    </Application_URLs>
    <Download_URLs>
      <Primary_Download_URL>https://github.com/sc0ty/subsync/releases/download/0.5/subsync-0.5.0-amd64.msi</Primary_Download_URL>
      <Secondary_Download_URL></Secondary_Download_URL>
      <Additional_Download_URL_1></Additional_Download_URL_1>
      <Additional_Download_URL_2></Additional_Download_URL_2>
    </Download_URLs>
  </Web_Info>
  <Program_Descriptions>
    <English>
      <Keywords>subtitle, subtitle synchronization, synchronization, subtitle synchronisation, synchronisation, speech, speech recognition</Keywords>
      <Char_Desc_45>Automatic movie subtitle synchronization tool</Char_Desc_45>
      <Char_Desc_80>Automatic movie subtitle synchronization by listening to audio track.</Char_Desc_80>
      <Char_Desc_250>This is an automatic movie subtitle synchronization tool. Synchronization is done by listening to the audio track. Tracks could be of different languages, it will be translated if necessary. Synchronization with another subtitles is also supported</Char_Desc_250>
      <Char_Desc_450>This is an automatic movie subtitle synchronization tool. Synchronization is done by listening to the audio track. You don't have to adjust subtitles manually.  Features: Subtitle synchronization with audio track. Subtitle synchronization with another subtitles. Support for different languages for subtitles and reference track (using dictionary). Character encoding auto detection. Easy to use graphical interface.</Char_Desc_450>
      <Char_Desc_2000>This is an automatic movie subtitle synchronization tool.
Synchronization is done by listening to the audio track.
Tracks could be of different languages, it will be translated if necessary.
Synchronization with another subtitles is also supported.
You don't have to adjust subtitles manually.

Features:
- subtitle synchronization with audio track
- subtitle synchronization with another subtitles
- support for different languages for subtitles and reference track (using dictionary)
- character encoding auto detection
- easy to use graphical interface
- support for drag &amp; drop;
- auto update</Char_Desc_2000>
    </English>
    <Polish>
      <Keywords>napisy, synchronizacja napis&#xF3;w, synchronizacja, mowa, rozpoznawanie mowy</Keywords>
      <Char_Desc_45>Automatyczna synchronizacja napis&#xF3;w do filmu</Char_Desc_45>
      <Char_Desc_80>Automatyczna synchronizacja napis&#xF3;w do filmu ze &#x15B;cie&#x17C;k&#x105; audio.</Char_Desc_80>
      <Char_Desc_250>Narz&#x119;dzie do automatycznej synchronizacji napis&#xF3;w do filmu. Synchronizacja odbywa si&#x119; poprzez s&#x142;uchanie &#x15B;cie&#x17C;ki audio. Audio nie musi by&#x107; w tym samym j&#x119;zyku co napisy. Mo&#x17C;liwa jest r&#xF3;wnie&#x17C; synchronizacja z innymi napisami.</Char_Desc_250>
      <Char_Desc_450>Narz&#x119;dzie do automatycznej synchronizacji napis&#xF3;w do filmu. Synchronizacja odbywa si&#x119; poprzez s&#x142;uchanie &#x15B;cie&#x17C;ki audio. Nie musisz d&#x142;u&#x17C;ej synchronizowa&#x107; napis&#xF3;w manualnie.  Opcje: Synchronizacja napis&#xF3;w ze &#x15B;cie&#x17C;k&#x105; audio. Synchronizacja napis&#xF3;w z innymi napisami. Napisy mog&#x105; by&#x107; w innym j&#x119;zyku co &#x15B;cie&#x17C;ka audio/napisy referencyjne/ Autodetekcja kodowania znak&#xF3;w. &#x141;atwy w u&#x17C;yciu interfejs graficzny.</Char_Desc_450>
      <Char_Desc_2000>Narz&#x119;dzie do automatycznej synchronizacji napis&#xF3;w do filmu.
Synchronizacja odbywa si&#x119; poprzez s&#x142;uchanie &#x15B;cie&#x17C;ki audio.
Nie musisz d&#x142;u&#x17C;ej synchronizowa&#x107; napis&#xF3;w manualnie.
Audio nie musi by&#x107; w tym samym j&#x119;zyku co napisy.
Mo&#x17C;liwa jest r&#xF3;wnie&#x17C; synchronizacja z innymi napisami (r&#xF3;wnie&#x17C; w odmiennym j&#x119;zyku).

Opcje:
- synchronizacja napis&#xF3;w ze &#x15B;cie&#x17C;k&#x105; audio
- synchronizacja napis&#xF3;w z innymi napisami
- napisy mog&#x105; by&#x107; w innym j&#x119;zyku co &#x15B;cie&#x17C;ka audio/napisy referencyjne
- autodetekcja kodowania znak&#xF3;w
- &#x142;atwy w u&#x17C;yciu interfejs graficzny
- aktualizacje automatyczne</Char_Desc_2000>
    </Polish>
  </Program_Descriptions>
  <Permissions>
    <Distribution_Permissions>https://www.gnu.org/licenses/gpl-3.0.html</Distribution_Permissions>
    <EULA>https://www.gnu.org/licenses/gpl-3.0.html</EULA>
  </Permissions>
  <Affiliates>
    <Affiliates_Regsoft_Order_Page></Affiliates_Regsoft_Order_Page>
    <Affiliates_Regnow_Order_Page></Affiliates_Regnow_Order_Page>
    <Affiliates_Regsoft_Vendor_ID></Affiliates_Regsoft_Vendor_ID>
    <Affiliates_Regnow_Vendor_ID></Affiliates_Regnow_Vendor_ID>
    <Affiliates_Regsoft_Product_ID></Affiliates_Regsoft_Product_ID>
    <Affiliates_Regnow_Product_ID></Affiliates_Regnow_Product_ID>
    <Affiliates_FORM></Affiliates_FORM>
    <Affiliates_FORM_VER></Affiliates_FORM_VER>
    <Affiliates_VERSION></Affiliates_VERSION>
    <Affiliates_URL></Affiliates_URL>
    <Affiliates_Information_Page></Affiliates_Information_Page>
    <Affiliates_Avangate_Order_Page></Affiliates_Avangate_Order_Page>
    <Affiliates_Avangate_Vendor_ID></Affiliates_Avangate_Vendor_ID>
    <Affiliates_Avangate_Product_ID></Affiliates_Avangate_Product_ID>
    <Affiliates_Avangate_Maximum_Commission_Rate></Affiliates_Avangate_Maximum_Commission_Rate>
    <Affiliates_BMTMicro_Order_Page></Affiliates_BMTMicro_Order_Page>
    <Affiliates_BMTMicro_Vendor_ID></Affiliates_BMTMicro_Vendor_ID>
    <Affiliates_BMTMicro_Product_ID></Affiliates_BMTMicro_Product_ID>
    <Affiliates_BMTMicro_Maximum_Commission_Rate></Affiliates_BMTMicro_Maximum_Commission_Rate>
    <Affiliates_eSellerate_Order_Page></Affiliates_eSellerate_Order_Page>
    <Affiliates_eSellerate_Vendor_ID></Affiliates_eSellerate_Vendor_ID>
    <Affiliates_eSellerate_Product_ID></Affiliates_eSellerate_Product_ID>
    <Affiliates_eSellerate_Maximum_Commission_Rate></Affiliates_eSellerate_Maximum_Commission_Rate>
    <Affiliates_Kagi_Order_Page></Affiliates_Kagi_Order_Page>
    <Affiliates_Kagi_Vendor_ID></Affiliates_Kagi_Vendor_ID>
    <Affiliates_Kagi_Product_ID></Affiliates_Kagi_Product_ID>
    <Affiliates_Kagi_Maximum_Commission_Rate></Affiliates_Kagi_Maximum_Commission_Rate>
    <Affiliates_Order1_Order_Page></Affiliates_Order1_Order_Page>
    <Affiliates_Order1_Vendor_ID></Affiliates_Order1_Vendor_ID>
    <Affiliates_Order1_Product_ID></Affiliates_Order1_Product_ID>
    <Affiliates_Order1_Maximum_Commission_Rate></Affiliates_Order1_Maximum_Commission_Rate>
    <Affiliates_Regnet_Order_Page></Affiliates_Regnet_Order_Page>
    <Affiliates_Regnet_Vendor_ID></Affiliates_Regnet_Vendor_ID>
    <Affiliates_Regnet_Product_ID></Affiliates_Regnet_Product_ID>
    <Affiliates_Regnet_Maximum_Commission_Rate></Affiliates_Regnet_Maximum_Commission_Rate>
    <Affiliates_Regnow_Maximum_Commission_Rate></Affiliates_Regnow_Maximum_Commission_Rate>
    <Affiliates_Regsoft_Maximum_Commission_Rate></Affiliates_Regsoft_Maximum_Commission_Rate>
    <Affiliates_ShareIt_Order_Page></Affiliates_ShareIt_Order_Page>
    <Affiliates_ShareIt_Vendor_ID></Affiliates_ShareIt_Vendor_ID>
    <Affiliates_ShareIt_Product_ID></Affiliates_ShareIt_Product_ID>
    <Affiliates_ShareIt_Maximum_Commission_Rate></Affiliates_ShareIt_Maximum_Commission_Rate>
    <Affiliates_SWReg_Order_Page></Affiliates_SWReg_Order_Page>
    <Affiliates_SWReg_Vendor_ID></Affiliates_SWReg_Vendor_ID>
    <Affiliates_SWReg_Product_ID></Affiliates_SWReg_Product_ID>
    <Affiliates_SWReg_Maximum_Commission_Rate></Affiliates_SWReg_Maximum_Commission_Rate>
  </Affiliates>
  <NewsFeed>
    <NewsFeed_FORM></NewsFeed_FORM>
    <NewsFeed_VERSION></NewsFeed_VERSION>
    <NewsFeed_URL></NewsFeed_URL>
    <NewsFeed_DESCRIPTION></NewsFeed_DESCRIPTION>
    <NewsFeed_Feed_URL></NewsFeed_Feed_URL>
    <NewsFeed_Type></NewsFeed_Type>
    <NewsFeed_Site_URL></NewsFeed_Site_URL>
    <NewsFeed_Author_First_Name>Michal</NewsFeed_Author_First_Name>
    <NewsFeed_Author_Last_Name>Szymaniak</NewsFeed_Author_Last_Name>
    <NewsFeed_Author_Email>sc0typl+subsync@gmail.com</NewsFeed_Author_Email>
    <NewsFeed_Language></NewsFeed_Language>
    <NewsFeed_Title></NewsFeed_Title>
    <NewsFeed_Description_70></NewsFeed_Description_70>
    <NewsFeed_Description_250></NewsFeed_Description_250>
    <NewsFeed_Purpose></NewsFeed_Purpose>
    <NewsFeed_Site_Name></NewsFeed_Site_Name>
  </NewsFeed>
  <Press_Release>
    <Press_Release></Press_Release>
    <Headline></Headline>
    <Summary></Summary>
    <Press_Release_Plain></Press_Release_Plain>
  </Press_Release>
  <Site>
    <Site_FORM></Site_FORM>
    <Site_VERSION></Site_VERSION>
    <Site_DESCRIPTION></Site_DESCRIPTION>
    <Site_Site_Title>Subtitle Speech Synchronizer</Site_Site_Title>
    <Site_Site_URL>https://sc0ty.github.io/subsync/</Site_Site_URL>
    <Site_Keywords></Site_Keywords>
    <Site_Description_100>Subtitle Speech Synchronizer</Site_Description_100>
    <Site_Description_250></Site_Description_250>
    <Site_Description_450></Site_Description_450>
    <Site_Contact_First_Name>Michal</Site_Contact_First_Name>
    <Site_Contact_Last_Name>Szymaniak</Site_Contact_Last_Name>
    <Site_Contact_Email>sc0typl+subsync@gmail.com</Site_Contact_Email>
  </Site>
  <Dynamic_PAD>
    <General>
      <DP_Pad_Enabled>TRUE</DP_Pad_Enabled>
      <DP_AtFormFill_Enabled>TRUE</DP_AtFormFill_Enabled>
      <DP_Distributive_Enabled>TRUE</DP_Distributive_Enabled>
      <DP_Script_Base_URL>http://repository.appvisor.com/</DP_Script_Base_URL>
      <DP_Pad_Mask>Subtitle_Speech_Synchronizer_pad.xml</DP_Pad_Mask>
      <DP_Distributive_Primary_URL>https://github.com/sc0ty/subsync/releases/download/0.5/subsync-0.5.0-amd64.msi</DP_Distributive_Primary_URL>
      <DP_Distributive_Mask>subsync-0.5.0-amd64.msi</DP_Distributive_Mask>
    </General>
  </Dynamic_PAD>
</XML_DIZ_INFO>
